{
	"name": "SQLstagingopssalesunit_ds",
	"properties": {
		"linkedServiceName": {
			"referenceName": "SQLdbConnection",
			"type": "LinkedServiceReference"
		},
		"annotations": [],
		"type": "AzureSqlTable",
		"schema": [
			{
				"name": "Sales_Unit_Code",
				"type": "nvarchar"
			},
			{
				"name": "Sales_Unit",
				"type": "nvarchar"
			},
			{
				"name": "Active_YN",
				"type": "nvarchar"
			},
			{
				"name": "Validation_Error",
				"type": "nvarchar"
			}
		],
		"typeProperties": {
			"schema": "staging",
			"table": "OPS_SALES_UNIT"
		}
	}
}